aiyt/launcher.py
aiyt/main.py
aiyt/style.css
aiyt/ui.py
aiyt/utils.py
aiyt/static/baloo.woff
aiyt-0.5.2.dist-info/METADATA
aiyt-0.5.2.dist-info/WHEEL
aiyt-0.5.2.dist-info/entry_points.txt
aiyt-0.5.2.dist-info/RECORD
