Metadata-Version: 2.4
Name: aiyt
Version: 0.5.2
Summary: Transcribe, Chat and Summarize Youtube Video with AI
Project-URL: License, https://opensource.org/licenses/MIT
Project-URL: repository, https://github.com/hoishing/aiyt
License: MIT
Requires-Python: >=3.12
Requires-Dist: click
Requires-Dist: google-genai
Requires-Dist: pytubefix
Requires-Dist: ruff
Requires-Dist: streamlit
Requires-Dist: watchdog
